[{
    "nome": "Lavender Brown",
    "ano_nascimento": "1979",
    "casa": "Grifin\u00f3ria"
}, {
    "nome": "Colin Creevey",
    "ano_nascimento": "1981",
    "casa": "Grifin\u00f3ria"
}, {
    "nome": "Seamus Finnigan",
    "ano_nascimento": "1979",
    "casa": "Grifin\u00f3ria"
}, {
    "nome": "Hermione Jean Granger",
    "ano_nascimento": "1979",
    "casa": "Grifin\u00f3ria"
}, {
    "nome": "Neville Longbottom",
    "ano_nascimento": "1980",
    "casa": "Grifin\u00f3ria"
}, {
    "nome": "Parvati Patil",
    "ano_nascimento": "1979",
    "casa": "Grifin\u00f3ria"
}, {
    "nome": "Harry James Potter",
    "ano_nascimento": "1980",
    "casa": "Grifin\u00f3ria"
}, {
    "nome": "Dean Thomas",
    "ano_nascimento": "1980",
    "casa": "Grifin\u00f3ria"
}, {
    "nome": "Romilda Vane",
    "ano_nascimento": "1981",
    "casa": "Grifin\u00f3ria"
}, {
    "nome": "Ginevra Molly Weasley",
    "ano_nascimento": "1981",
    "casa": "Grifin\u00f3ria"
}, {
    "nome": "Ronald Bilius Weasley",
    "ano_nascimento": "1980",
    "casa": "Grifin\u00f3ria"
}, {
    "nome": "Hannah Abbott",
    "ano_nascimento": "1980",
    "casa": "Lufa-Lufa"
}, {
    "nome": "Susan Bones",
    "ano_nascimento": "1979",
    "casa": "Lufa-Lufa"
}, {
    "nome": "Cedric Diggory",
    "ano_nascimento": "1977",
    "casa": "Lufa-Lufa"
}, {
    "nome": "Justin Finch-Fletchley",
    "ano_nascimento": "1979",
    "casa": "Lufa-Lufa"
}, {
    "nome": "Ernest Macmillan",
    "ano_nascimento": "1980",
    "casa": "Lufa-Lufa"
}, {
    "nome": "Terry Boot",
    "ano_nascimento": "1980",
    "casa": "Corvinal"
}, {
    "nome": "Mandy Brocklehurst",
    "ano_nascimento": "1979",
    "casa": "Corvinal"
}, {
    "nome": "Cho Chang",
    "ano_nascimento": "1979",
    "casa": "Corvinal"
}, {
    "nome": "Penelope Clearwater",
    "ano_nascimento": "1976",
    "casa": "Corvinal"
}, {
    "nome": "Michael Corner",
    "ano_nascimento": "1979",
    "casa": "Corvinal"
}, {
    "nome": "Roger Davies",
    "ano_nascimento": "1978",
    "casa": "Corvinal"
}, {
    "nome": "Marietta Edgecombe",
    "ano_nascimento": "1978",
    "casa": "Corvinal"
}, {
    "nome": "Anthony Goldstein",
    "ano_nascimento": "1980",
    "casa": "Corvinal"
}, {
    "nome": "Robert Hilliard",
    "ano_nascimento": "1974",
    "casa": "Corvinal"
}, {
    "nome": "Luna Lovegood",
    "ano_nascimento": "1981",
    "casa": "Corvinal"
}, {
    "nome": "Isobel MacDougal",
    "ano_nascimento": "1980",
    "casa": "Corvinal"
}, {
    "nome": "Padma Patil",
    "ano_nascimento": "1979",
    "casa": "Corvinal"
}, {
    "nome": "Lisa Turpin",
    "ano_nascimento": "1979",
    "casa": "Corvinal"
}, {
    "nome": "Millicent Bulstrode",
    "ano_nascimento": "1979",
    "casa": "Sonserina"
}, {
    "nome": "Vincent Crabbe",
    "ano_nascimento": "1979",
    "casa": "Sonserina"
}, {
    "nome": "Tracey Davis",
    "ano_nascimento": "1980",
    "casa": "Sonserina"
}, {
    "nome": "Marcus Flint",
    "ano_nascimento": "1975",
    "casa": "Sonserina"
}, {
    "nome": "Gregory Goyle",
    "ano_nascimento": "1980",
    "casa": "Sonserina"
}, {
    "nome": "Terence Higgs",
    "ano_nascimento": "1979",
    "casa": "Sonserina"
}, {
    "nome": "Draco Lucius Malfoy",
    "ano_nascimento": "1980",
    "casa": "Sonserina"
}, {
    "nome": "Adelaide Murton",
    "ano_nascimento": "1982",
    "casa": "Sonserina"
}, {
    "nome": "Pansy Parkinson",
    "ano_nascimento": "1979",
    "casa": "Sonserina"
}, {
    "nome": "Adrian Pucey",
    "ano_nascimento": "1977",
    "casa": "Sonserina"
}, {
    "nome": "Blaise Zabini",
    "ano_nascimento": "1979",
    "casa": "Sonserina"
}]